functions_by_vladalt/math_functions.py
functions_by_vladalt-0.3.0.dist-info/WHEEL
functions_by_vladalt-0.3.0.dist-info/METADATA
functions_by_vladalt-0.3.0.dist-info/RECORD
