Metadata-Version: 2.1
Name: functions-by-vladalt
Version: 0.3.0
Summary: This is our testproject
Author: Vladyslav Altyok
Author-email: vladyslav.altyok@gmail.com
Requires-Python: >=3.10,<4.0
Classifier: Programming Language :: Python :: 3
Classifier: Programming Language :: Python :: 3.10
Classifier: Programming Language :: Python :: 3.11
